[
  {
    "date": "2022-04-12",
    "commits": [
      {
        "sha": "0fcc1ed01fd5ef9124584bb4b55ca43125e65558",
        "commit": {
          "author": {
            "name": "omer Korkmaz",
            "email": "h.omr.korkmaz@gmail.com",
            "date": "2022-04-12T00:21:21Z"
          },
          "message": "Added categories"
        },
        "html_url": "https://github.com/Omr-Korkmaz/Landing-Page-NextJs-inprogress/commit/0fcc1ed01fd5ef9124584bb4b55ca43125e65558",
        "author": {
          "login": "Omr-Korkmaz",
          "avatar_url": "https://avatars.githubusercontent.com/u/39599546?v=4"
        },
        "committer": {
          "name": "omer Korkmaz",
          "email": "h.omr.korkmaz@gmail.com",
          "avatar_url": "https://avatars.githubusercontent.com/u/39599546?v=4", 
          "html_url": "https://github.com/Omr-Korkmaz"
        },
        "repository": "Landing-Page-NextJs-inprogress",
        "timeAgo": "1 year ago"
      }
    ]
  }
]
